sall/__init__.py
sall/cli.py
sall/utils.py
sall/commands/__init__.py
sall/commands/images.py
tests/__init__.py
tests/test_images.py
mailopt-0.1.0.dist-info/METADATA
mailopt-0.1.0.dist-info/WHEEL
mailopt-0.1.0.dist-info/entry_points.txt
mailopt-0.1.0.dist-info/top_level.txt
mailopt-0.1.0.dist-info/RECORD
